{
  "project_info": {
    "project_number": "14671332776",
    "project_id": "emarkting",
    "storage_bucket": "emarkting.appspot.com"
  },
  "client": [
    {
      "client_info": {
        "mobilesdk_app_id": "1:14671332776:android:a6917313b3f4fc3fe6c99d",
        "android_client_info": {
          "package_name": "com.LeRoiZaid.e_markting"
        }
      },
      "oauth_client": [],
      "api_key": [
        {
          "current_key": "AIzaSyCB7ke0G4GJtJFWQ_3l8eGdeigndUapdkk"
        }
      ],
      "services": {
        "appinvite_service": {
          "other_platform_oauth_client": []
        }
      }
    }
  ],
  "configuration_version": "1"
}